trrsheadset/__init__.py
trrsheadset/__main__.py
trrsheadset/controller.py
trrsheadset/runner.py
trrsheadset-0.0.1a2.dist-info/LICENSE
trrsheadset-0.0.1a2.dist-info/METADATA
trrsheadset-0.0.1a2.dist-info/WHEEL
trrsheadset-0.0.1a2.dist-info/top_level.txt
trrsheadset-0.0.1a2.dist-info/RECORD
