Metadata-Version: 2.1
Name: trrsheadset
Version: 0.0.1a2
Summary: Provide support of 3.5mm headset controls for PC
Home-page: https://github.com/PaperStrike/HeadsetControlsPC
Author: PaperStrike
Author-email: 1395348685z@gmail.com
License: UNKNOWN
Project-URL: Bug Tracker, https://github.com/PaperStrike/HeadsetControlsPC/issues
Platform: UNKNOWN
Classifier: Development Status :: 3 - Alpha
Classifier: Programming Language :: Python :: 3
Classifier: License :: OSI Approved :: GNU General Public License v3 (GPLv3)
Classifier: Operating System :: Microsoft :: Windows
Classifier: Operating System :: POSIX :: Linux
Requires-Python: >=3.6
Requires-Dist: sounddevice
Requires-Dist: numpy
Requires-Dist: keyboard
